mcp_server_time/__init__.py
mcp_server_time/__main__.py
mcp_server_time/app.py
mcp_server_time/server.py
baiyx_mcp_server_time_20240408-0.6.12.dist-info/METADATA
baiyx_mcp_server_time_20240408-0.6.12.dist-info/WHEEL
baiyx_mcp_server_time_20240408-0.6.12.dist-info/entry_points.txt
baiyx_mcp_server_time_20240408-0.6.12.dist-info/RECORD
