Metadata-Version: 2.4
Name: baiyx-mcp-server-time-20240408
Version: 0.6.12
Summary: A Model Context Protocol server providing time and timezone conversion functionality
Author-email: baiyx <baiyx@example.com>
License: MIT
Keywords: llm,mcp,time,timezone
Classifier: Development Status :: 4 - Beta
Classifier: Intended Audience :: Developers
Classifier: License :: OSI Approved :: MIT License
Classifier: Programming Language :: Python :: 3
Classifier: Programming Language :: Python :: 3.10
Requires-Python: >=3.10
Requires-Dist: fastapi>=0.110.0
Requires-Dist: mcp>=1.0.0
Requires-Dist: pydantic>=2.0.0
Requires-Dist: uvicorn>=0.27.1
